odoo/addons/stock_buffer_route/README.rst
odoo/addons/stock_buffer_route/__init__.py
odoo/addons/stock_buffer_route/__manifest__.py
odoo/addons/stock_buffer_route/i18n/stock_buffer_route.pot
odoo/addons/stock_buffer_route/models/__init__.py
odoo/addons/stock_buffer_route/models/stock_buffer.py
odoo/addons/stock_buffer_route/readme/CONTRIBUTORS.rst
odoo/addons/stock_buffer_route/readme/DESCRIPTION.rst
odoo/addons/stock_buffer_route/readme/USAGE.rst
odoo/addons/stock_buffer_route/static/description/icon.png
odoo/addons/stock_buffer_route/static/description/index.html
odoo/addons/stock_buffer_route/tests/__init__.py
odoo/addons/stock_buffer_route/tests/test_stock_buffer_route.py
odoo/addons/stock_buffer_route/views/stock_buffer_views.xml
odoo13_addon_stock_buffer_route-13.0.1.3.1.dist-info/METADATA
odoo13_addon_stock_buffer_route-13.0.1.3.1.dist-info/WHEEL
odoo13_addon_stock_buffer_route-13.0.1.3.1.dist-info/top_level.txt
odoo13_addon_stock_buffer_route-13.0.1.3.1.dist-info/RECORD
